pystse-0.0.1.dist-info/METADATA
pystse-0.0.1.dist-info/WHEEL
pystse-0.0.1.dist-info/license_files/LICENSE
_safetensors_rust/__init__.py
_safetensors_rust/_safetensors_rust.cp311-win_amd64.pyd
pystse-0.0.1.dist-info/RECORD
